django_watcher/__init__.py
django_watcher/abstract_watcher.py
django_watcher/decorators/__init__.py
django_watcher/decorators/helpers.py
django_watcher/decorators/model.py
django_watcher/decorators/queryset.py
django_watcher/decorators/querytools.py
django_watcher/mixins.py
django_watcher-1.2.3.dist-info/LICENSE
django_watcher-1.2.3.dist-info/WHEEL
django_watcher-1.2.3.dist-info/METADATA
django_watcher-1.2.3.dist-info/RECORD
